MimirNotes
