Metadata-Version: 1.0
Name: MimirNotes
Version: 0.6.5
Summary: A simple, command line, note taking utility.
Home-page: https://github.com/jcerise/mimir
Author: Jeremy Cerise
Author-email: jcerise06@gmail.com
License: UNKNOWN
Keywords: note terminal command-line journal
Platform: UNKNOWN
